rsrtools/__init__.py
rsrtools/importrsm.py
rsrtools/utils.py
rsrtools/files/__init__.py
rsrtools/files/config.py
rsrtools/files/exceptions.py
rsrtools/files/profilemanager.py
rsrtools/files/savefile.py
rsrtools/files/steam.py
rsrtools/files/steamcache.py
rsrtools/files/welder.py
rsrtools/songlists/__init__.py
rsrtools/songlists/config.py
rsrtools/songlists/configclasses.py
rsrtools/songlists/database.py
rsrtools/songlists/scanner.py
rsrtools/songlists/songlists.py
rsrtools-1.1.0.dist-info/METADATA
rsrtools-1.1.0.dist-info/WHEEL
rsrtools-1.1.0.dist-info/entry_points.txt
rsrtools-1.1.0.dist-info/licenses/LICENSE
rsrtools-1.1.0.dist-info/RECORD
