Metadata-Version: 2.1
Name: rsrtools
Version: 1.1.0
Summary: Tools for managing Rocksmith 2014 songlists and save files.
Project-URL: Homepage, https://github.com/BuongiornoTexas/rsrtools
Project-URL: Bug Tracker, https://github.com/BuongiornoTexas/rsrtools/issues
Author: BuongiornoTexas
License-Expression: MIT
License-File: LICENSE
Keywords: Rocksmith,Songlists
Classifier: Development Status :: 5 - Production/Stable
Classifier: Environment :: Console
Classifier: Intended Audience :: End Users/Desktop
Classifier: License :: OSI Approved :: MIT License
Classifier: Operating System :: MacOS :: MacOS X
Classifier: Operating System :: Microsoft :: Windows :: Windows 10
Classifier: Operating System :: Microsoft :: Windows :: Windows 11
Classifier: Programming Language :: Python
Classifier: Programming Language :: Python :: 3.12
Classifier: Topic :: Games/Entertainment
Requires-Python: >=3.12
Requires-Dist: pycryptodome>=3.20.0
Requires-Dist: pydantic>=2.6.1
Requires-Dist: simplejson>=3.19.2
Requires-Dist: tomli-w>=1.0.0
Provides-Extra: dev
Requires-Dist: types-simplejson; extra == 'dev'
